torch_lib_with_rust-0.1.1.dist-info/METADATA
torch_lib_with_rust-0.1.1.dist-info/WHEEL
torch_lib_with_rust/__init__.py
torch_lib_with_rust/torch_lib_with_rust.abi3.so
torch_lib_with_rust-0.1.1.dist-info/RECORD
