Metadata-Version: 2.3
Name: torch-lib-with-rust
Version: 0.1.1
Requires-Dist: numpy
Requires-Dist: torch ==2.3.0
Requires-Dist: patchelf
